zero_totp_db_model/__init__.py
zero_totp_db_model/model.py
zero_totp_db_model/model_init.py
zero_totp_db_model-2.3.0.dist-info/licenses/LICENSE
zero_totp_db_model-2.3.0.dist-info/METADATA
zero_totp_db_model-2.3.0.dist-info/WHEEL
zero_totp_db_model-2.3.0.dist-info/top_level.txt
zero_totp_db_model-2.3.0.dist-info/RECORD
