Metadata-Version: 2.4
Name: zero_totp_db_model
Version: 2.3.0
Summary: Zero-TOTP Database Model
Author: Seaweedbrain
Author-email: developer@zero-totp.com
Keywords: Zero-TOTP,database
License-File: LICENSE
Dynamic: author
Dynamic: author-email
Dynamic: description
Dynamic: keywords
Dynamic: license-file
Dynamic: summary
